{"per_page":10,"total":30,"current":21,"data":[{"year":"2023","months":[{"month":"Apr","entries":[{"title":"微信小程序-icon组件","date":"2023-04-22T12:25:14.000Z","date_formatted":{"ll":"Apr 22, 2023","L":"04/22/2023","MM-DD":"04-22"},"link":"2023/04/22/Web/微信小程序/component/常用组件/34-微信小程序-icon组件"},{"title":"微信小程序-text组件","date":"2023-04-22T03:52:01.000Z","date_formatted":{"ll":"Apr 22, 2023","L":"04/22/2023","MM-DD":"04-22"},"link":"2023/04/22/Web/微信小程序/component/常用组件/33-微信小程序-text组件"},{"title":"微信小程序-view组件","date":"2023-04-22T02:48:56.000Z","date_formatted":{"ll":"Apr 22, 2023","L":"04/22/2023","MM-DD":"04-22"},"link":"2023/04/22/Web/微信小程序/component/常用组件/32-微信小程序-view组件"},{"title":"微信小程序-案例练习","date":"2023-04-20T16:27:16.000Z","date_formatted":{"ll":"Apr 21, 2023","L":"04/21/2023","MM-DD":"04-21"},"link":"2023/04/21/Web/微信小程序/example/31-微信小程序-案例练习"},{"title":"微信小程序-touches和changedTouches","date":"2023-04-20T15:45:36.000Z","date_formatted":{"ll":"Apr 20, 2023","L":"04/20/2023","MM-DD":"04-20"},"link":"2023/04/20/Web/微信小程序/event/30-微信小程序-touches和changedTouches"},{"title":"微信小程序-data和mark","date":"2023-04-18T16:47:55.000Z","date_formatted":{"ll":"Apr 19, 2023","L":"04/19/2023","MM-DD":"04-19"},"link":"2023/04/19/Web/微信小程序/event/29-微信小程序-data和mark"},{"title":"微信小程序-事件传递数据","date":"2023-04-16T04:21:22.000Z","date_formatted":{"ll":"Apr 16, 2023","L":"04/16/2023","MM-DD":"04-16"},"link":"2023/04/16/Web/微信小程序/event/28-微信小程序-事件传递数据"},{"title":"微信小程序-小程序事件冒泡和事件捕获","date":"2023-04-16T03:36:46.000Z","date_formatted":{"ll":"Apr 16, 2023","L":"04/16/2023","MM-DD":"04-16"},"link":"2023/04/16/Web/微信小程序/event/27-微信小程序-小程序事件冒泡和事件捕获"},{"title":"微信小程序-小程序事件绑定","date":"2023-04-14T13:28:29.000Z","date_formatted":{"ll":"Apr 14, 2023","L":"04/14/2023","MM-DD":"04-14"},"link":"2023/04/14/Web/微信小程序/event/26-微信小程序-小程序事件绑定"},{"title":"微信小程序-WXS支持的语法","date":"2023-04-14T13:02:44.000Z","date_formatted":{"ll":"Apr 14, 2023","L":"04/14/2023","MM-DD":"04-14"},"link":"2023/04/14/Web/微信小程序/wxs/25-微信小程序-WXS支持的语法"}]}]}]}